gwprice/__init__.py
gwprice/__main__.py
gwprice/dev_utils/__init__.py
gwprice/dev_utils/price_source_files.py
gwprice/py.typed
gridworks_ps-0.0.1.dist-info/LICENSE
gridworks_ps-0.0.1.dist-info/METADATA
gridworks_ps-0.0.1.dist-info/WHEEL
gridworks_ps-0.0.1.dist-info/entry_points.txt
gridworks_ps-0.0.1.dist-info/RECORD
