Metadata-Version: 2.1
Name: gridworks-ps
Version: 0.0.1
Summary: GridWorks Price Service
Home-page: https://github.com/thegridelectric/gridworks-ps
License: MIT
Author: gridworks
Author-email: gridworks@gridworks-consulting.com
Requires-Python: >=3.10,<4.0
Classifier: Development Status :: 2 - Pre-Alpha
Classifier: License :: OSI Approved :: MIT License
Classifier: Programming Language :: Python :: 3
Classifier: Programming Language :: Python :: 3.10
Classifier: Programming Language :: Python :: 3.11
Requires-Dist: gridworks (>=0.2.7,<0.3.0)
Project-URL: Changelog, https://github.com/thegridelectric/gridworks-ps/releases
Project-URL: Documentation, https://gridworks-ps.readthedocs.io
Project-URL: Repository, https://github.com/thegridelectric/gridworks-ps
